odoo/addons/stock_storage_type_buffer/README.rst
odoo/addons/stock_storage_type_buffer/__init__.py
odoo/addons/stock_storage_type_buffer/__manifest__.py
odoo/addons/stock_storage_type_buffer/i18n/es_AR.po
odoo/addons/stock_storage_type_buffer/i18n/it.po
odoo/addons/stock_storage_type_buffer/i18n/pt_BR.po
odoo/addons/stock_storage_type_buffer/i18n/stock_storage_type_buffer.pot
odoo/addons/stock_storage_type_buffer/models/__init__.py
odoo/addons/stock_storage_type_buffer/models/stock_location.py
odoo/addons/stock_storage_type_buffer/models/stock_location_storage_buffer.py
odoo/addons/stock_storage_type_buffer/readme/CONTRIBUTORS.md
odoo/addons/stock_storage_type_buffer/readme/DESCRIPTION.md
odoo/addons/stock_storage_type_buffer/security/ir.model.access.csv
odoo/addons/stock_storage_type_buffer/static/description/icon.png
odoo/addons/stock_storage_type_buffer/static/description/index.html
odoo/addons/stock_storage_type_buffer/templates/stock_location_storage_buffer_templates.xml
odoo/addons/stock_storage_type_buffer/tests/__init__.py
odoo/addons/stock_storage_type_buffer/tests/test_storage_type_buffer.py
odoo/addons/stock_storage_type_buffer/views/stock_location_storage_buffer_views.xml
odoo_addon_stock_storage_type_buffer-18.0.1.0.1.dist-info/METADATA
odoo_addon_stock_storage_type_buffer-18.0.1.0.1.dist-info/WHEEL
odoo_addon_stock_storage_type_buffer-18.0.1.0.1.dist-info/top_level.txt
odoo_addon_stock_storage_type_buffer-18.0.1.0.1.dist-info/RECORD
